{
"10xgenomics": 30,
"6sense": 35,
"86repairs": 1,
"airtable": 33,
"aiserajobs": 5,
"alku": 11,
"apolloio": 41,
"aptoslabs": 6,
"atomiccartoons": 2,
"awin": 48,
"banyaninfrastructure": 4,
"bitso": 8,
"carefeed": 2,
"coalition": 30,
"collibra": 37,
"crunchyroll": 68,
"devtechnology": 16,
"diracinc": 7,
"dnsfilter": 6,
"edmentum": 22,
"elevatebio": 18,
"fixify": 8,
"flexport": 106,
"foresightmentalhealth": 7,
"givedirectly": 25,
"go1eu": 3,
"gumgum": 13,
"hillhousehome": 37,
"ibkr": 176,
"instacart": 163,
"kurosbiosciencesinc": 9,
"lenusehealth": 13,
"logicgate": 13,
"manychat": 7,
"monograph": 3,
"motional": 103,
"newsweek": 14,
"northbeam": 9,
"nozominetworks": 20,
"ntx": 1,
"ocrolusinc": 11,
"pagerduty": 37,
"pivotbio": 18,
"prove": 11,
"quilt": 3,
"recursionpharmaceuticals": 30,
"relativity": 304,
"roofr": 3,
"sendbird": 16,
"similarweb": 83,
"sofi": 100,
"stackav": 21,
"tireseasycom": 6,
"urby": 3,
"wehrtyou": 73,
"zaviant": 4,
"zestyai": 6
}